{
    "declaration": {
        "attributes": {
            "version": "1.0",
            "encoding": "UTF-8"
        }
    },
    "elements": [
        {
            "type": "element",
            "name": "gpx",
            "attributes": {
                "xmlns": "http://www.topografix.com/GPX/1/1",
                "version": "1.1",
                "creator": "FME(R) 2017.0.1.1"
            },
            "elements": [
                {
                    "type": "element",
                    "name": "metadata",
                    "elements": [
                        {
                            "type": "element",
                            "name": "time",
                            "elements": [
                                {
                                    "type": "text",
                                    "text": "2018-03-17T10:19:03+01:00"
                                }
                            ]
                        },
                        {
                            "type": "element",
                            "name": "bounds",
                            "attributes": {
                                "minlat": "49.878886900922659",
                                "minlon": "6.0370193535237879",
                                "maxlat": "49.891854356527844",
                                "maxlon": "6.0668777252769939"
                            }
                        }
                    ]
                },
                {
                    "type": "element",
                    "name": "trk",
                    "elements": [
                        {
                            "type": "element",
                            "name": "name",
                            "elements": [
                                {
                                    "type": "text",
                                    "text": "00 Autopedestres : Welscheid 1"
                                }
                            ]
                        },
                        {
                            "type": "element",
                            "name": "trkseg",
                            "elements": [
                                {
                                    "type": "element",
                                    "name": "trkpt",
                                    "attributes": {
                                        "lat": "49.887002715642595",
                                        "lon": "6.0660681297654877"
                                    }
                                },
                                {
                                    "type": "element",
                                    "name": "trkpt",
                                    "attributes": {
                                        "lat": "49.886983706103564",
                                        "lon": "6.0663148929945612"
                                    }
                                },
                                {
                                    "type": "element",
                                    "name": "trkpt",
                                    "attributes": {
                                        "lat": "49.886886930152244",
                                        "lon": "6.0664248635640226"
                                    }
                                },
                                {
                                    "type": "element",
                                    "name": "trkpt",
                                    "attributes": {
                                        "lat": "49.886846157425474",
                                        "lon": "6.0665254517860321"
                                    }
                                },
                                {
                                    "type": "element",
                                    "name": "trkpt",
                                    "attributes": {
                                        "lat": "49.886592373389398",
                                        "lon": "6.0667555776464104"
                                    }
                                },
                                {
                                    "type": "element",
                                    "name": "trkpt",
                                    "attributes": {
                                        "lat": "49.886403677146291",
                                        "lon": "6.0668777252769939"
                                    }
                                },
                                {
                                    "type": "element",
                                    "name": "trkpt",
                                    "attributes": {
                                        "lat": "49.886293506708647",
                                        "lon": "6.0668362088172687"
                                    }
                                },
                                {
                                    "type": "element",
                                    "name": "trkpt",
                                    "attributes": {
                                        "lat": "49.886019020278106",
                                        "lon": "6.0665202148856023"
                                    }
                                },
                                {
                                    "type": "element",
                                    "name": "trkpt",
                                    "attributes": {
                                        "lat": "49.885755819644238",
                                        "lon": "6.0662598601330338"
                                    }
                                },
                                {
                                    "type": "element",
                                    "name": "trkpt",
                                    "attributes": {
                                        "lat": "49.885380163547808",
                                        "lon": "6.065916255268518"
                                    }
                                },
                                {
                                    "type": "element",
                                    "name": "trkpt",
                                    "attributes": {
                                        "lat": "49.885317120176708",
                                        "lon": "6.0657911552452815"
                                    }
                                },
                                {
                                    "type": "element",
                                    "name": "trkpt",
                                    "attributes": {
                                        "lat": "49.884791137660784",
                                        "lon": "6.0650070632580384"
                                    }
                                },
                                {
                                    "type": "element",
                                    "name": "trkpt",
                                    "attributes": {
                                        "lat": "49.884764860875705",
                                        "lon": "6.0649573474852572"
                                    }
                                },
                                {
                                    "type": "element",
                                    "name": "trkpt",
                                    "attributes": {
                                        "lat": "49.8844213651046",
                                        "lon": "6.0644363776385246"
                                    }
                                },
                                {
                                    "type": "element",
                                    "name": "trkpt",
                                    "attributes": {
                                        "lat": "49.884210150345325",
                                        "lon": "6.0642672350329905"
                                    }
                                },
                                {
                                    "type": "element",
                                    "name": "trkpt",
                                    "attributes": {
                                        "lat": "49.884153118406395",
                                        "lon": "6.0642323663158253"
                                    }
                                },
                                {
                                    "type": "element",
                                    "name": "trkpt",
                                    "attributes": {
                                        "lat": "49.884054608535003",
                                        "lon": "6.0642135908527441"
                                    }
                                },
                                {
                                    "type": "element",
                                    "name": "trkpt",
                                    "attributes": {
                                        "lat": "49.883937087723737",
                                        "lon": "6.0642645528240111"
                                    }
                                },
                                {
                                    "type": "element",
                                    "name": "trkpt",
                                    "attributes": {
                                        "lat": "49.883762534226079",
                                        "lon": "6.0644818117541153"
                                    }
                                },
                                {
                                    "type": "element",
                                    "name": "trkpt",
                                    "attributes": {
                                        "lat": "49.883572052820064",
                                        "lon": "6.0647721206221394"
                                    }
                                },
                                {
                                    "type": "element",
                                    "name": "trkpt",
                                    "attributes": {
                                        "lat": "49.883377131694068",
                                        "lon": "6.0650665333190776"
                                    }
                                },
                                {
                                    "type": "element",
                                    "name": "trkpt",
                                    "attributes": {
                                        "lat": "49.883237141671799",
                                        "lon": "6.0652489235320068"
                                    }
                                },
                                {
                                    "type": "element",
                                    "name": "trkpt",
                                    "attributes": {
                                        "lat": "49.883152456152615",
                                        "lon": "6.0653401186384714"
                                    }
                                },
                                {
                                    "type": "element",
                                    "name": "trkpt",
                                    "attributes": {
                                        "lat": "49.883000076523238",
                                        "lon": "6.0654379706074133"
                                    }
                                },
                                {
                                    "type": "element",
                                    "name": "trkpt",
                                    "attributes": {
                                        "lat": "49.882837617659824",
                                        "lon": "6.0655238012958632"
                                    }
                                },
                                {
                                    "type": "element",
                                    "name": "trkpt",
                                    "attributes": {
                                        "lat": "49.882563581740285",
                                        "lon": "6.065591694456903"
                                    }
                                },
                                {
                                    "type": "element",
                                    "name": "trkpt",
                                    "attributes": {
                                        "lat": "49.882273605640776",
                                        "lon": "6.0655575186815884"
                                    }
                                },
                                {
                                    "type": "element",
                                    "name": "trkpt",
                                    "attributes": {
                                        "lat": "49.882157073775979",
                                        "lon": "6.065502343623848"
                                    }
                                },
                                {
                                    "type": "element",
                                    "name": "trkpt",
                                    "attributes": {
                                        "lat": "49.882071223410385",
                                        "lon": "6.0654501122497795"
                                    }
                                },
                                {
                                    "type": "element",
                                    "name": "trkpt",
                                    "attributes": {
                                        "lat": "49.881923750950158",
                                        "lon": "6.0653226356199852"
                                    }
                                },
                                {
                                    "type": "element",
                                    "name": "trkpt",
                                    "attributes": {
                                        "lat": "49.881702525303439",
                                        "lon": "6.065032957046574"
                                    }
                                },
                                {
                                    "type": "element",
                                    "name": "trkpt",
                                    "attributes": {
                                        "lat": "49.881497416292504",
                                        "lon": "6.0647034643541176"
                                    }
                                },
                                {
                                    "type": "element",
                                    "name": "trkpt",
                                    "attributes": {
                                        "lat": "49.881112368969575",
                                        "lon": "6.0639146912025872"
                                    }
                                },
                                {
                                    "type": "element",
                                    "name": "trkpt",
                                    "attributes": {
                                        "lat": "49.880826090602369",
                                        "lon": "6.0629900628818216"
                                    }
                                },
                                {
                                    "type": "element",
                                    "name": "trkpt",
                                    "attributes": {
                                        "lat": "49.88055784274249",
                                        "lon": "6.0621280161501998"
                                    }
                                },
                                {
                                    "type": "element",
                                    "name": "trkpt",
                                    "attributes": {
                                        "lat": "49.880532888286858",
                                        "lon": "6.061874152839331"
                                    }
                                },
                                {
                                    "type": "element",
                                    "name": "trkpt",
                                    "attributes": {
                                        "lat": "49.880572565131871",
                                        "lon": "6.0614518627245246"
                                    }
                                },
                                {
                                    "type": "element",
                                    "name": "trkpt",
                                    "attributes": {
                                        "lat": "49.88061231762029",
                                        "lon": "6.0609958871922514"
                                    }
                                },
                                {
                                    "type": "element",
                                    "name": "trkpt",
                                    "attributes": {
                                        "lat": "49.880709086636138",
                                        "lon": "6.0603815640809717"
                                    }
                                },
                                {
                                    "type": "element",
                                    "name": "trkpt",
                                    "attributes": {
                                        "lat": "49.880693067507558",
                                        "lon": "6.0600720277816036"
                                    }
                                },
                                {
                                    "type": "element",
                                    "name": "trkpt",
                                    "attributes": {
                                        "lat": "49.880573077422653",
                                        "lon": "6.0591401023500939"
                                    }
                                },
                                {
                                    "type": "element",
                                    "name": "trkpt",
                                    "attributes": {
                                        "lat": "49.880563439621163",
                                        "lon": "6.0584479374220868"
                                    }
                                },
                                {
                                    "type": "element",
                                    "name": "trkpt",
                                    "attributes": {
                                        "lat": "49.880518352945494",
                                        "lon": "6.0583054275657444"
                                    }
                                },
                                {
                                    "type": "element",
                                    "name": "trkpt",
                                    "attributes": {
                                        "lat": "49.880451465200167",
                                        "lon": "6.0581848125140629"
                                    }
                                },
                                {
                                    "type": "element",
                                    "name": "trkpt",
                                    "attributes": {
                                        "lat": "49.880372027353076",
                                        "lon": "6.0580622750121984"
                                    }
                                },
                                {
                                    "type": "element",
                                    "name": "trkpt",
                                    "attributes": {
                                        "lat": "49.880198788613349",
                                        "lon": "6.0578817940947811"
                                    }
                                },
                                {
                                    "type": "element",
                                    "name": "trkpt",
                                    "attributes": {
                                        "lat": "49.88003010727008",
                                        "lon": "6.0577673915844699"
                                    }
                                },
                                {
                                    "type": "element",
                                    "name": "trkpt",
                                    "attributes": {
                                        "lat": "49.879821653303523",
                                        "lon": "6.0576853601301988"
                                    }
                                },
                                {
                                    "type": "element",
                                    "name": "trkpt",
                                    "attributes": {
                                        "lat": "49.879494968282074",
                                        "lon": "6.0575564281949106"
                                    }
                                },
                                {
                                    "type": "element",
                                    "name": "trkpt",
                                    "attributes": {
                                        "lat": "49.879256563616529",
                                        "lon": "6.0573934913337419"
                                    }
                                },
                                {
                                    "type": "element",
                                    "name": "trkpt",
                                    "attributes": {
                                        "lat": "49.87912384072559",
                                        "lon": "6.0572755328793964"
                                    }
                                },
                                {
                                    "type": "element",
                                    "name": "trkpt",
                                    "attributes": {
                                        "lat": "49.878995503988882",
                                        "lon": "6.057042784130827"
                                    }
                                },
                                {
                                    "type": "element",
                                    "name": "trkpt",
                                    "attributes": {
                                        "lat": "49.8789466462134",
                                        "lon": "6.0567935371901616"
                                    }
                                },
                                {
                                    "type": "element",
                                    "name": "trkpt",
                                    "attributes": {
                                        "lat": "49.878893810087462",
                                        "lon": "6.0564656336752298"
                                    }
                                },
                                {
                                    "type": "element",
                                    "name": "trkpt",
                                    "attributes": {
                                        "lat": "49.878886900922659",
                                        "lon": "6.056291739307091"
                                    }
                                },
                                {
                                    "type": "element",
                                    "name": "trkpt",
                                    "attributes": {
                                        "lat": "49.878927165294527",
                                        "lon": "6.0560899110973576"
                                    }
                                },
                                {
                                    "type": "element",
                                    "name": "trkpt",
                                    "attributes": {
                                        "lat": "49.878974075346711",
                                        "lon": "6.0557871991899974"
                                    }
                                },
                                {
                                    "type": "element",
                                    "name": "trkpt",
                                    "attributes": {
                                        "lat": "49.879064402804488",
                                        "lon": "6.055544491623869"
                                    }
                                },
                                {
                                    "type": "element",
                                    "name": "trkpt",
                                    "attributes": {
                                        "lat": "49.879252243311257",
                                        "lon": "6.0552265640424787"
                                    }
                                },
                                {
                                    "type": "element",
                                    "name": "trkpt",
                                    "attributes": {
                                        "lat": "49.879522275981692",
                                        "lon": "6.0548756118728724"
                                    }
                                },
                                {
                                    "type": "element",
                                    "name": "trkpt",
                                    "attributes": {
                                        "lat": "49.879761824336939",
                                        "lon": "6.0545714713225856"
                                    }
                                },
                                {
                                    "type": "element",
                                    "name": "trkpt",
                                    "attributes": {
                                        "lat": "49.880069793226212",
                                        "lon": "6.0539421601667156"
                                    }
                                },
                                {
                                    "type": "element",
                                    "name": "trkpt",
                                    "attributes": {
                                        "lat": "49.880239601062378",
                                        "lon": "6.0535755657618262"
                                    }
                                },
                                {
                                    "type": "element",
                                    "name": "trkpt",
                                    "attributes": {
                                        "lat": "49.880401028175292",
                                        "lon": "6.0531647460219249"
                                    }
                                },
                                {
                                    "type": "element",
                                    "name": "trkpt",
                                    "attributes": {
                                        "lat": "49.88058985158905",
                                        "lon": "6.0525217864302494"
                                    }
                                },
                                {
                                    "type": "element",
                                    "name": "trkpt",
                                    "attributes": {
                                        "lat": "49.880804795799598",
                                        "lon": "6.0516864755319162"
                                    }
                                },
                                {
                                    "type": "element",
                                    "name": "trkpt",
                                    "attributes": {
                                        "lat": "49.881102146933955",
                                        "lon": "6.0507560674477272"
                                    }
                                },
                                {
                                    "type": "element",
                                    "name": "trkpt",
                                    "attributes": {
                                        "lat": "49.881182859159999",
                                        "lon": "6.0505541279263557"
                                    }
                                },
                                {
                                    "type": "element",
                                    "name": "trkpt",
                                    "attributes": {
                                        "lat": "49.881681147206471",
                                        "lon": "6.0498711599827324"
                                    }
                                },
                                {
                                    "type": "element",
                                    "name": "trkpt",
                                    "attributes": {
                                        "lat": "49.881811379976",
                                        "lon": "6.0497421430219696"
                                    }
                                },
                                {
                                    "type": "element",
                                    "name": "trkpt",
                                    "attributes": {
                                        "lat": "49.882125802543449",
                                        "lon": "6.0494978895483111"
                                    }
                                },
                                {
                                    "type": "element",
                                    "name": "trkpt",
                                    "attributes": {
                                        "lat": "49.882431350742159",
                                        "lon": "6.049368443642507"
                                    }
                                },
                                {
                                    "type": "element",
                                    "name": "trkpt",
                                    "attributes": {
                                        "lat": "49.882851482349103",
                                        "lon": "6.049193496518817"
                                    }
                                },
                                {
                                    "type": "element",
                                    "name": "trkpt",
                                    "attributes": {
                                        "lat": "49.883015443095147",
                                        "lon": "6.0490783062962379"
                                    }
                                },
                                {
                                    "type": "element",
                                    "name": "trkpt",
                                    "attributes": {
                                        "lat": "49.883116444999068",
                                        "lon": "6.0489389195265408"
                                    }
                                },
                                {
                                    "type": "element",
                                    "name": "trkpt",
                                    "attributes": {
                                        "lat": "49.883172493957154",
                                        "lon": "6.0487996421311374"
                                    }
                                },
                                {
                                    "type": "element",
                                    "name": "trkpt",
                                    "attributes": {
                                        "lat": "49.883382984365753",
                                        "lon": "6.0480303728800608"
                                    }
                                },
                                {
                                    "type": "element",
                                    "name": "trkpt",
                                    "attributes": {
                                        "lat": "49.883448044259346",
                                        "lon": "6.0479119426420942"
                                    }
                                },
                                {
                                    "type": "element",
                                    "name": "trkpt",
                                    "attributes": {
                                        "lat": "49.883686788846724",
                                        "lon": "6.0477557951070127"
                                    }
                                },
                                {
                                    "type": "element",
                                    "name": "trkpt",
                                    "attributes": {
                                        "lat": "49.884000604902582",
                                        "lon": "6.047562723794683"
                                    }
                                },
                                {
                                    "type": "element",
                                    "name": "trkpt",
                                    "attributes": {
                                        "lat": "49.884207315818074",
                                        "lon": "6.0474926411567331"
                                    }
                                },
                                {
                                    "type": "element",
                                    "name": "trkpt",
                                    "attributes": {
                                        "lat": "49.884288169722694",
                                        "lon": "6.0474333051364173"
                                    }
                                },
                                {
                                    "type": "element",
                                    "name": "trkpt",
                                    "attributes": {
                                        "lat": "49.884313623490335",
                                        "lon": "6.0473392796667333"
                                    }
                                },
                                {
                                    "type": "element",
                                    "name": "trkpt",
                                    "attributes": {
                                        "lat": "49.884312710341597",
                                        "lon": "6.0472558361485467"
                                    }
                                },
                                {
                                    "type": "element",
                                    "name": "trkpt",
                                    "attributes": {
                                        "lat": "49.884296703065431",
                                        "lon": "6.0469915028001004"
                                    }
                                },
                                {
                                    "type": "element",
                                    "name": "trkpt",
                                    "attributes": {
                                        "lat": "49.884251577058862",
                                        "lon": "6.0468246425944709"
                                    }
                                },
                                {
                                    "type": "element",
                                    "name": "trkpt",
                                    "attributes": {
                                        "lat": "49.884195274089834",
                                        "lon": "6.0467169464797355"
                                    }
                                },
                                {
                                    "type": "element",
                                    "name": "trkpt",
                                    "attributes": {
                                        "lat": "49.884145474908856",
                                        "lon": "6.0463796480365808"
                                    }
                                },
                                {
                                    "type": "element",
                                    "name": "trkpt",
                                    "attributes": {
                                        "lat": "49.884106978354147",
                                        "lon": "6.0461049364117487"
                                    }
                                },
                                {
                                    "type": "element",
                                    "name": "trkpt",
                                    "attributes": {
                                        "lat": "49.884048307015846",
                                        "lon": "6.0458824544276517"
                                    }
                                },
                                {
                                    "type": "element",
                                    "name": "trkpt",
                                    "attributes": {
                                        "lat": "49.884005452563173",
                                        "lon": "6.0457399404091019"
                                    }
                                },
                                {
                                    "type": "element",
                                    "name": "trkpt",
                                    "attributes": {
                                        "lat": "49.883951348798071",
                                        "lon": "6.0455870192011671"
                                    }
                                },
                                {
                                    "type": "element",
                                    "name": "trkpt",
                                    "attributes": {
                                        "lat": "49.883773408993996",
                                        "lon": "6.0452291751280169"
                                    }
                                },
                                {
                                    "type": "element",
                                    "name": "trkpt",
                                    "attributes": {
                                        "lat": "49.883392860922832",
                                        "lon": "6.0445692138304512"
                                    }
                                },
                                {
                                    "type": "element",
                                    "name": "trkpt",
                                    "attributes": {
                                        "lat": "49.883260025625013",
                                        "lon": "6.0443573607689434"
                                    }
                                },
                                {
                                    "type": "element",
                                    "name": "trkpt",
                                    "attributes": {
                                        "lat": "49.882812261852692",
                                        "lon": "6.0439028154623697"
                                    }
                                },
                                {
                                    "type": "element",
                                    "name": "trkpt",
                                    "attributes": {
                                        "lat": "49.88246579460376",
                                        "lon": "6.0435027604030847"
                                    }
                                },
                                {
                                    "type": "element",
                                    "name": "trkpt",
                                    "attributes": {
                                        "lat": "49.882386292646281",
                                        "lon": "6.0433847432065049"
                                    }
                                },
                                {
                                    "type": "element",
                                    "name": "trkpt",
                                    "attributes": {
                                        "lat": "49.882388020951119",
                                        "lon": "6.0433284168172268"
                                    }
                                },
                                {
                                    "type": "element",
                                    "name": "trkpt",
                                    "attributes": {
                                        "lat": "49.882449787672861",
                                        "lon": "6.0433367498024841"
                                    }
                                },
                                {
                                    "type": "element",
                                    "name": "trkpt",
                                    "attributes": {
                                        "lat": "49.882917545249619",
                                        "lon": "6.0435686119349663"
                                    }
                                },
                                {
                                    "type": "element",
                                    "name": "trkpt",
                                    "attributes": {
                                        "lat": "49.883272927815845",
                                        "lon": "6.0438077220551856"
                                    }
                                },
                                {
                                    "type": "element",
                                    "name": "trkpt",
                                    "attributes": {
                                        "lat": "49.883758695054588",
                                        "lon": "6.0440673752710978"
                                    }
                                },
                                {
                                    "type": "element",
                                    "name": "trkpt",
                                    "attributes": {
                                        "lat": "49.884120904239758",
                                        "lon": "6.0443864831967549"
                                    }
                                },
                                {
                                    "type": "element",
                                    "name": "trkpt",
                                    "attributes": {
                                        "lat": "49.884294182237177",
                                        "lon": "6.044584323294659"
                                    }
                                },
                                {
                                    "type": "element",
                                    "name": "trkpt",
                                    "attributes": {
                                        "lat": "49.884610032528059",
                                        "lon": "6.0450819405700909"
                                    }
                                },
                                {
                                    "type": "element",
                                    "name": "trkpt",
                                    "attributes": {
                                        "lat": "49.884890916229814",
                                        "lon": "6.0456368380382672"
                                    }
                                },
                                {
                                    "type": "element",
                                    "name": "trkpt",
                                    "attributes": {
                                        "lat": "49.885005877241397",
                                        "lon": "6.0459531058502751"
                                    }
                                },
                                {
                                    "type": "element",
                                    "name": "trkpt",
                                    "attributes": {
                                        "lat": "49.88507119327015",
                                        "lon": "6.0460816522090086"
                                    }
                                },
                                {
                                    "type": "element",
                                    "name": "trkpt",
                                    "attributes": {
                                        "lat": "49.885192634740989",
                                        "lon": "6.0461474427971584"
                                    }
                                },
                                {
                                    "type": "element",
                                    "name": "trkpt",
                                    "attributes": {
                                        "lat": "49.885331977386599",
                                        "lon": "6.0461366583004841"
                                    }
                                },
                                {
                                    "type": "element",
                                    "name": "trkpt",
                                    "attributes": {
                                        "lat": "49.885483167309786",
                                        "lon": "6.0460815971114519"
                                    }
                                },
                                {
                                    "type": "element",
                                    "name": "trkpt",
                                    "attributes": {
                                        "lat": "49.885606061986323",
                                        "lon": "6.0460142187222568"
                                    }
                                },
                                {
                                    "type": "element",
                                    "name": "trkpt",
                                    "attributes": {
                                        "lat": "49.885819394696554",
                                        "lon": "6.0458293133875847"
                                    }
                                },
                                {
                                    "type": "element",
                                    "name": "trkpt",
                                    "attributes": {
                                        "lat": "49.885942876300881",
                                        "lon": "6.0456968127375763"
                                    }
                                },
                                {
                                    "type": "element",
                                    "name": "trkpt",
                                    "attributes": {
                                        "lat": "49.886111058426359",
                                        "lon": "6.0453241672055036"
                                    }
                                },
                                {
                                    "type": "element",
                                    "name": "trkpt",
                                    "attributes": {
                                        "lat": "49.886183320589758",
                                        "lon": "6.0450223114910093"
                                    }
                                },
                                {
                                    "type": "element",
                                    "name": "trkpt",
                                    "attributes": {
                                        "lat": "49.886358220380991",
                                        "lon": "6.0443727484209493"
                                    }
                                },
                                {
                                    "type": "element",
                                    "name": "trkpt",
                                    "attributes": {
                                        "lat": "49.886368065627053",
                                        "lon": "6.0439320235529781"
                                    }
                                },
                                {
                                    "type": "element",
                                    "name": "trkpt",
                                    "attributes": {
                                        "lat": "49.886464009403326",
                                        "lon": "6.0432708170529459"
                                    }
                                },
                                {
                                    "type": "element",
                                    "name": "trkpt",
                                    "attributes": {
                                        "lat": "49.886524289672472",
                                        "lon": "6.0428914786840888"
                                    }
                                },
                                {
                                    "type": "element",
                                    "name": "trkpt",
                                    "attributes": {
                                        "lat": "49.886620527149212",
                                        "lon": "6.0425085679762445"
                                    }
                                },
                                {
                                    "type": "element",
                                    "name": "trkpt",
                                    "attributes": {
                                        "lat": "49.886811122819246",
                                        "lon": "6.0420871453978444"
                                    }
                                },
                                {
                                    "type": "element",
                                    "name": "trkpt",
                                    "attributes": {
                                        "lat": "49.887255466159019",
                                        "lon": "6.0414493754240013"
                                    }
                                },
                                {
                                    "type": "element",
                                    "name": "trkpt",
                                    "attributes": {
                                        "lat": "49.88762144550639",
                                        "lon": "6.0410935837146704"
                                    }
                                },
                                {
                                    "type": "element",
                                    "name": "trkpt",
                                    "attributes": {
                                        "lat": "49.887978558351939",
                                        "lon": "6.0408526120693926"
                                    }
                                },
                                {
                                    "type": "element",
                                    "name": "trkpt",
                                    "attributes": {
                                        "lat": "49.888329026484762",
                                        "lon": "6.0407021051811451"
                                    }
                                },
                                {
                                    "type": "element",
                                    "name": "trkpt",
                                    "attributes": {
                                        "lat": "49.888551553842916",
                                        "lon": "6.0407119602357833"
                                    }
                                },
                                {
                                    "type": "element",
                                    "name": "trkpt",
                                    "attributes": {
                                        "lat": "49.888812294797724",
                                        "lon": "6.0407251944282105"
                                    }
                                },
                                {
                                    "type": "element",
                                    "name": "trkpt",
                                    "attributes": {
                                        "lat": "49.889003286912683",
                                        "lon": "6.0406725113373501"
                                    }
                                },
                                {
                                    "type": "element",
                                    "name": "trkpt",
                                    "attributes": {
                                        "lat": "49.889106545217899",
                                        "lon": "6.0405504785390418"
                                    }
                                },
                                {
                                    "type": "element",
                                    "name": "trkpt",
                                    "attributes": {
                                        "lat": "49.889217148815518",
                                        "lon": "6.0403806971339717"
                                    }
                                },
                                {
                                    "type": "element",
                                    "name": "trkpt",
                                    "attributes": {
                                        "lat": "49.889522308940563",
                                        "lon": "6.0399067572990086"
                                    }
                                },
                                {
                                    "type": "element",
                                    "name": "trkpt",
                                    "attributes": {
                                        "lat": "49.889683127079316",
                                        "lon": "6.0395818132912185"
                                    }
                                },
                                {
                                    "type": "element",
                                    "name": "trkpt",
                                    "attributes": {
                                        "lat": "49.889952781191937",
                                        "lon": "6.0389315055227692"
                                    }
                                },
                                {
                                    "type": "element",
                                    "name": "trkpt",
                                    "attributes": {
                                        "lat": "49.890068732781565",
                                        "lon": "6.0386866915416233"
                                    }
                                },
                                {
                                    "type": "element",
                                    "name": "trkpt",
                                    "attributes": {
                                        "lat": "49.89034688704217",
                                        "lon": "6.0381884519690852"
                                    }
                                },
                                {
                                    "type": "element",
                                    "name": "trkpt",
                                    "attributes": {
                                        "lat": "49.890840870376508",
                                        "lon": "6.0377418149980961"
                                    }
                                },
                                {
                                    "type": "element",
                                    "name": "trkpt",
                                    "attributes": {
                                        "lat": "49.891242757377562",
                                        "lon": "6.0373476025020709"
                                    }
                                },
                                {
                                    "type": "element",
                                    "name": "trkpt",
                                    "attributes": {
                                        "lat": "49.891530169891197",
                                        "lon": "6.0370928560597354"
                                    }
                                },
                                {
                                    "type": "element",
                                    "name": "trkpt",
                                    "attributes": {
                                        "lat": "49.891615501901036",
                                        "lon": "6.0370230442605326"
                                    }
                                },
                                {
                                    "type": "element",
                                    "name": "trkpt",
                                    "attributes": {
                                        "lat": "49.891694165202324",
                                        "lon": "6.0370193535237879"
                                    }
                                },
                                {
                                    "type": "element",
                                    "name": "trkpt",
                                    "attributes": {
                                        "lat": "49.891730876692229",
                                        "lon": "6.037103729511851"
                                    }
                                },
                                {
                                    "type": "element",
                                    "name": "trkpt",
                                    "attributes": {
                                        "lat": "49.891757379950597",
                                        "lon": "6.0372696807336164"
                                    }
                                },
                                {
                                    "type": "element",
                                    "name": "trkpt",
                                    "attributes": {
                                        "lat": "49.891722994133019",
                                        "lon": "6.0374242390820791"
                                    }
                                },
                                {
                                    "type": "element",
                                    "name": "trkpt",
                                    "attributes": {
                                        "lat": "49.89139005264655",
                                        "lon": "6.0384222498708615"
                                    }
                                },
                                {
                                    "type": "element",
                                    "name": "trkpt",
                                    "attributes": {
                                        "lat": "49.891244446294408",
                                        "lon": "6.0388644820149002"
                                    }
                                },
                                {
                                    "type": "element",
                                    "name": "trkpt",
                                    "attributes": {
                                        "lat": "49.891166328685934",
                                        "lon": "6.0393621985111885"
                                    }
                                },
                                {
                                    "type": "element",
                                    "name": "trkpt",
                                    "attributes": {
                                        "lat": "49.891139816631522",
                                        "lon": "6.0397797586636006"
                                    }
                                },
                                {
                                    "type": "element",
                                    "name": "trkpt",
                                    "attributes": {
                                        "lat": "49.891169760456016",
                                        "lon": "6.0404407062405996"
                                    }
                                },
                                {
                                    "type": "element",
                                    "name": "trkpt",
                                    "attributes": {
                                        "lat": "49.891260159444016",
                                        "lon": "6.0408927515245185"
                                    }
                                },
                                {
                                    "type": "element",
                                    "name": "trkpt",
                                    "attributes": {
                                        "lat": "49.891301063374051",
                                        "lon": "6.0413031780707822"
                                    }
                                },
                                {
                                    "type": "element",
                                    "name": "trkpt",
                                    "attributes": {
                                        "lat": "49.891312599665191",
                                        "lon": "6.041577996694496"
                                    }
                                },
                                {
                                    "type": "element",
                                    "name": "trkpt",
                                    "attributes": {
                                        "lat": "49.891400686476679",
                                        "lon": "6.0419743857659656"
                                    }
                                },
                                {
                                    "type": "element",
                                    "name": "trkpt",
                                    "attributes": {
                                        "lat": "49.891585270325606",
                                        "lon": "6.0422313627055271"
                                    }
                                },
                                {
                                    "type": "element",
                                    "name": "trkpt",
                                    "attributes": {
                                        "lat": "49.891715786812384",
                                        "lon": "6.0423736697991757"
                                    }
                                },
                                {
                                    "type": "element",
                                    "name": "trkpt",
                                    "attributes": {
                                        "lat": "49.891785590787251",
                                        "lon": "6.042491780178004"
                                    }
                                },
                                {
                                    "type": "element",
                                    "name": "trkpt",
                                    "attributes": {
                                        "lat": "49.891835307917084",
                                        "lon": "6.0427421497147868"
                                    }
                                },
                                {
                                    "type": "element",
                                    "name": "trkpt",
                                    "attributes": {
                                        "lat": "49.89182667541769",
                                        "lon": "6.0430761687420027"
                                    }
                                },
                                {
                                    "type": "element",
                                    "name": "trkpt",
                                    "attributes": {
                                        "lat": "49.891854356527844",
                                        "lon": "6.0437406126327922"
                                    }
                                },
                                {
                                    "type": "element",
                                    "name": "trkpt",
                                    "attributes": {
                                        "lat": "49.891818937821526",
                                        "lon": "6.0442521355499323"
                                    }
                                },
                                {
                                    "type": "element",
                                    "name": "trkpt",
                                    "attributes": {
                                        "lat": "49.891810492153184",
                                        "lon": "6.0447670686025461"
                                    }
                                },
                                {
                                    "type": "element",
                                    "name": "trkpt",
                                    "attributes": {
                                        "lat": "49.8917861496817",
                                        "lon": "6.0451289597775171"
                                    }
                                },
                                {
                                    "type": "element",
                                    "name": "trkpt",
                                    "attributes": {
                                        "lat": "49.891748789685174",
                                        "lon": "6.0453144237643563"
                                    }
                                },
                                {
                                    "type": "element",
                                    "name": "trkpt",
                                    "attributes": {
                                        "lat": "49.891687688888737",
                                        "lon": "6.0455432238587745"
                                    }
                                },
                                {
                                    "type": "element",
                                    "name": "trkpt",
                                    "attributes": {
                                        "lat": "49.891627155967981",
                                        "lon": "6.0456894990477279"
                                    }
                                },
                                {
                                    "type": "element",
                                    "name": "trkpt",
                                    "attributes": {
                                        "lat": "49.891595805697733",
                                        "lon": "6.0458009095109952"
                                    }
                                },
                                {
                                    "type": "element",
                                    "name": "trkpt",
                                    "attributes": {
                                        "lat": "49.891600439319866",
                                        "lon": "6.045933104342553"
                                    }
                                },
                                {
                                    "type": "element",
                                    "name": "trkpt",
                                    "attributes": {
                                        "lat": "49.89143429248309",
                                        "lon": "6.0461039968640309"
                                    }
                                },
                                {
                                    "type": "element",
                                    "name": "trkpt",
                                    "attributes": {
                                        "lat": "49.891328831545671",
                                        "lon": "6.0462747365625988"
                                    }
                                },
                                {
                                    "type": "element",
                                    "name": "trkpt",
                                    "attributes": {
                                        "lat": "49.89122566508582",
                                        "lon": "6.046490697964928"
                                    }
                                },
                                {
                                    "type": "element",
                                    "name": "trkpt",
                                    "attributes": {
                                        "lat": "49.891013539199818",
                                        "lon": "6.0472088923886664"
                                    }
                                },
                                {
                                    "type": "element",
                                    "name": "trkpt",
                                    "attributes": {
                                        "lat": "49.890717883945726",
                                        "lon": "6.0482115932446536"
                                    }
                                },
                                {
                                    "type": "element",
                                    "name": "trkpt",
                                    "attributes": {
                                        "lat": "49.890538209748094",
                                        "lon": "6.0487928779773794"
                                    }
                                },
                                {
                                    "type": "element",
                                    "name": "trkpt",
                                    "attributes": {
                                        "lat": "49.89042148291955",
                                        "lon": "6.0491332895503653"
                                    }
                                },
                                {
                                    "type": "element",
                                    "name": "trkpt",
                                    "attributes": {
                                        "lat": "49.890278626626035",
                                        "lon": "6.0494651210237302"
                                    }
                                },
                                {
                                    "type": "element",
                                    "name": "trkpt",
                                    "attributes": {
                                        "lat": "49.890111913422523",
                                        "lon": "6.049728955563296"
                                    }
                                },
                                {
                                    "type": "element",
                                    "name": "trkpt",
                                    "attributes": {
                                        "lat": "49.889930066192711",
                                        "lon": "6.0499381368094491"
                                    }
                                },
                                {
                                    "type": "element",
                                    "name": "trkpt",
                                    "attributes": {
                                        "lat": "49.889669488067227",
                                        "lon": "6.0500848853021392"
                                    }
                                },
                                {
                                    "type": "element",
                                    "name": "trkpt",
                                    "attributes": {
                                        "lat": "49.889020194898336",
                                        "lon": "6.0503578132619689"
                                    }
                                },
                                {
                                    "type": "element",
                                    "name": "trkpt",
                                    "attributes": {
                                        "lat": "49.888575309978805",
                                        "lon": "6.050505001142862"
                                    }
                                },
                                {
                                    "type": "element",
                                    "name": "trkpt",
                                    "attributes": {
                                        "lat": "49.888422561675256",
                                        "lon": "6.0505958205653743"
                                    }
                                },
                                {
                                    "type": "element",
                                    "name": "trkpt",
                                    "attributes": {
                                        "lat": "49.888343974827187",
                                        "lon": "6.0506760242213353"
                                    }
                                },
                                {
                                    "type": "element",
                                    "name": "trkpt",
                                    "attributes": {
                                        "lat": "49.888263154260436",
                                        "lon": "6.0507701485001402"
                                    }
                                },
                                {
                                    "type": "element",
                                    "name": "trkpt",
                                    "attributes": {
                                        "lat": "49.887978786133829",
                                        "lon": "6.0511962287251855"
                                    }
                                },
                                {
                                    "type": "element",
                                    "name": "trkpt",
                                    "attributes": {
                                        "lat": "49.887772168553141",
                                        "lon": "6.0513512499095707"
                                    }
                                },
                                {
                                    "type": "element",
                                    "name": "trkpt",
                                    "attributes": {
                                        "lat": "49.887673666067037",
                                        "lon": "6.051415622925906"
                                    }
                                },
                                {
                                    "type": "element",
                                    "name": "trkpt",
                                    "attributes": {
                                        "lat": "49.887462835508956",
                                        "lon": "6.0514799959422536"
                                    }
                                },
                                {
                                    "type": "element",
                                    "name": "trkpt",
                                    "attributes": {
                                        "lat": "49.887189660708465",
                                        "lon": "6.051649388620711"
                                    }
                                },
                                {
                                    "type": "element",
                                    "name": "trkpt",
                                    "attributes": {
                                        "lat": "49.886999696295604",
                                        "lon": "6.0517884499788472"
                                    }
                                },
                                {
                                    "type": "element",
                                    "name": "trkpt",
                                    "attributes": {
                                        "lat": "49.88670010137686",
                                        "lon": "6.0520784455149474"
                                    }
                                },
                                {
                                    "type": "element",
                                    "name": "trkpt",
                                    "attributes": {
                                        "lat": "49.886475644612453",
                                        "lon": "6.0523885880456509"
                                    }
                                },
                                {
                                    "type": "element",
                                    "name": "trkpt",
                                    "attributes": {
                                        "lat": "49.886341016915502",
                                        "lon": "6.0526219829242232"
                                    }
                                },
                                {
                                    "type": "element",
                                    "name": "trkpt",
                                    "attributes": {
                                        "lat": "49.886317055708844",
                                        "lon": "6.0527308567952769"
                                    }
                                },
                                {
                                    "type": "element",
                                    "name": "trkpt",
                                    "attributes": {
                                        "lat": "49.886197833073915",
                                        "lon": "6.0532971952744399"
                                    }
                                },
                                {
                                    "type": "element",
                                    "name": "trkpt",
                                    "attributes": {
                                        "lat": "49.886083497064497",
                                        "lon": "6.0535966343187173"
                                    }
                                },
                                {
                                    "type": "element",
                                    "name": "trkpt",
                                    "attributes": {
                                        "lat": "49.88598480872146",
                                        "lon": "6.0538090674796914"
                                    }
                                },
                                {
                                    "type": "element",
                                    "name": "trkpt",
                                    "attributes": {
                                        "lat": "49.885924340022846",
                                        "lon": "6.05403184652865"
                                    }
                                },
                                {
                                    "type": "element",
                                    "name": "trkpt",
                                    "attributes": {
                                        "lat": "49.885913234180258",
                                        "lon": "6.0541675421206351"
                                    }
                                },
                                {
                                    "type": "element",
                                    "name": "trkpt",
                                    "attributes": {
                                        "lat": "49.88585160218085",
                                        "lon": "6.0548330945836906"
                                    }
                                },
                                {
                                    "type": "element",
                                    "name": "trkpt",
                                    "attributes": {
                                        "lat": "49.885735463990116",
                                        "lon": "6.0555986775379216"
                                    }
                                },
                                {
                                    "type": "element",
                                    "name": "trkpt",
                                    "attributes": {
                                        "lat": "49.885584814161973",
                                        "lon": "6.0562207330697246"
                                    }
                                },
                                {
                                    "type": "element",
                                    "name": "trkpt",
                                    "attributes": {
                                        "lat": "49.8854974422457",
                                        "lon": "6.0565200997493349"
                                    }
                                },
                                {
                                    "type": "element",
                                    "name": "trkpt",
                                    "attributes": {
                                        "lat": "49.885314112518323",
                                        "lon": "6.0569828935882999"
                                    }
                                },
                                {
                                    "type": "element",
                                    "name": "trkpt",
                                    "attributes": {
                                        "lat": "49.885114081031091",
                                        "lon": "6.0575576143368517"
                                    }
                                },
                                {
                                    "type": "element",
                                    "name": "trkpt",
                                    "attributes": {
                                        "lat": "49.88499979630285",
                                        "lon": "6.0579231306965919"
                                    }
                                },
                                {
                                    "type": "element",
                                    "name": "trkpt",
                                    "attributes": {
                                        "lat": "49.884973080065265",
                                        "lon": "6.0581945249874627"
                                    }
                                },
                                {
                                    "type": "element",
                                    "name": "trkpt",
                                    "attributes": {
                                        "lat": "49.884989156380456",
                                        "lon": "6.0585597461740299"
                                    }
                                },
                                {
                                    "type": "element",
                                    "name": "trkpt",
                                    "attributes": {
                                        "lat": "49.885086376942887",
                                        "lon": "6.0591717701454835"
                                    }
                                },
                                {
                                    "type": "element",
                                    "name": "trkpt",
                                    "attributes": {
                                        "lat": "49.885273454697185",
                                        "lon": "6.0597348958813608"
                                    }
                                },
                                {
                                    "type": "element",
                                    "name": "trkpt",
                                    "attributes": {
                                        "lat": "49.885473919272322",
                                        "lon": "6.0601936361005535"
                                    }
                                },
                                {
                                    "type": "element",
                                    "name": "trkpt",
                                    "attributes": {
                                        "lat": "49.885668342739102",
                                        "lon": "6.0607055496475111"
                                    }
                                },
                                {
                                    "type": "element",
                                    "name": "trkpt",
                                    "attributes": {
                                        "lat": "49.88579981459069",
                                        "lon": "6.0609403096408538"
                                    }
                                },
                                {
                                    "type": "element",
                                    "name": "trkpt",
                                    "attributes": {
                                        "lat": "49.885955920165017",
                                        "lon": "6.0612883644997764"
                                    }
                                },
                                {
                                    "type": "element",
                                    "name": "trkpt",
                                    "attributes": {
                                        "lat": "49.886012380587637",
                                        "lon": "6.0614338360992832"
                                    }
                                },
                                {
                                    "type": "element",
                                    "name": "trkpt",
                                    "attributes": {
                                        "lat": "49.886069410330002",
                                        "lon": "6.0616484128203449"
                                    }
                                },
                                {
                                    "type": "element",
                                    "name": "trkpt",
                                    "attributes": {
                                        "lat": "49.886307764416664",
                                        "lon": "6.0626234293844652"
                                    }
                                },
                                {
                                    "type": "element",
                                    "name": "trkpt",
                                    "attributes": {
                                        "lat": "49.886425164192026",
                                        "lon": "6.063204126120521"
                                    }
                                },
                                {
                                    "type": "element",
                                    "name": "trkpt",
                                    "attributes": {
                                        "lat": "49.886486286273289",
                                        "lon": "6.0636910196905331"
                                    }
                                },
                                {
                                    "type": "element",
                                    "name": "trkpt",
                                    "attributes": {
                                        "lat": "49.88654507826449",
                                        "lon": "6.0640874718567082"
                                    }
                                },
                                {
                                    "type": "element",
                                    "name": "trkpt",
                                    "attributes": {
                                        "lat": "49.88657047428778",
                                        "lon": "6.0648457864181502"
                                    }
                                },
                                {
                                    "type": "element",
                                    "name": "trkpt",
                                    "attributes": {
                                        "lat": "49.886647283202933",
                                        "lon": "6.0652874266097498"
                                    }
                                },
                                {
                                    "type": "element",
                                    "name": "trkpt",
                                    "attributes": {
                                        "lat": "49.886800665295347",
                                        "lon": "6.0659063250240326"
                                    }
                                },
                                {
                                    "type": "element",
                                    "name": "trkpt",
                                    "attributes": {
                                        "lat": "49.886833357667115",
                                        "lon": "6.0660761763924942"
                                    }
                                },
                                {
                                    "type": "element",
                                    "name": "trkpt",
                                    "attributes": {
                                        "lat": "49.887002715642602",
                                        "lon": "6.066073494183513"
                                    }
                                }
                            ]
                        }
                    ]
                }
            ]
        }
    ]
}